multiCMD.py
multicmd-1.44.dist-info/METADATA
multicmd-1.44.dist-info/WHEEL
multicmd-1.44.dist-info/entry_points.txt
multicmd-1.44.dist-info/top_level.txt
multicmd-1.44.dist-info/RECORD
