Metadata-Version: 2.4
Name: multiCMD
Version: 1.44
Summary: Run commands simultaneously
Home-page: https://github.com/yufei-pan/multiCMD
Author: Yufei Pan
Author-email: pan@zopyr.us
License: GPLv3+
Classifier: Programming Language :: Python :: 3
Classifier: License :: OSI Approved :: GNU General Public License v3 or later (GPLv3+)
Classifier: Operating System :: POSIX :: Linux
Classifier: Operating System :: Microsoft :: Windows
Requires-Python: >=3.6
Requires-Dist: argparse
Dynamic: author
Dynamic: author-email
Dynamic: classifier
Dynamic: description
Dynamic: description-content-type
Dynamic: home-page
Dynamic: license
Dynamic: requires-dist
Dynamic: requires-python
Dynamic: summary
